zsp_parser/core.cpython-38-x86_64-linux-gnu.so
zsp_parser/__version__.py
zsp_parser/ast_decl.pxd
zsp_parser/core.pxd
zsp_parser/decl.pxd
zsp_parser/pkginfo.py
zsp_parser/libantlr4-runtime.so.4.8
zsp_parser/libzsp-parser.so
zsp_parser/__build_num__.py
zsp_parser/libast.so
zsp_parser/parser.py
zsp_parser/ast.cpython-38-x86_64-linux-gnu.so
zsp_parser/ast.pxd
zsp_parser/__init__.py
zsp_parser/core.pyi
zsp_parser/ast.pyi
zsp_parser/utils/symbol_type_scope_util.py
zsp_parser/utils/symbol_children_scope_util.py
zsp_parser/utils/symbol_scope_util.py
zsp_parser/utils/__init__.py
zsp_parser/utils/list_iterator.py
zsp_parser/share/include/PyParserUtils.h
zsp_parser/share/include/PyBaseVisitor.h
zsp_parser/share/include/antlr4-runtime/BufferedTokenStream.h
zsp_parser/share/include/antlr4-runtime/TokenSource.h
zsp_parser/share/include/antlr4-runtime/RuleContextWithAltNum.h
zsp_parser/share/include/antlr4-runtime/CommonTokenStream.h
zsp_parser/share/include/antlr4-runtime/BaseErrorListener.h
zsp_parser/share/include/antlr4-runtime/antlr4-runtime.h
zsp_parser/share/include/antlr4-runtime/ListTokenSource.h
zsp_parser/share/include/antlr4-runtime/NoViableAltException.h
zsp_parser/share/include/antlr4-runtime/FailedPredicateException.h
zsp_parser/share/include/antlr4-runtime/ANTLRFileStream.h
zsp_parser/share/include/antlr4-runtime/DefaultErrorStrategy.h
zsp_parser/share/include/antlr4-runtime/BailErrorStrategy.h
zsp_parser/share/include/antlr4-runtime/WritableToken.h
zsp_parser/share/include/antlr4-runtime/Exceptions.h
zsp_parser/share/include/antlr4-runtime/Recognizer.h
zsp_parser/share/include/antlr4-runtime/InterpreterRuleContext.h
zsp_parser/share/include/antlr4-runtime/CharStream.h
zsp_parser/share/include/antlr4-runtime/CommonTokenFactory.h
zsp_parser/share/include/antlr4-runtime/CommonToken.h
zsp_parser/share/include/antlr4-runtime/RuntimeMetaData.h
zsp_parser/share/include/antlr4-runtime/UnbufferedTokenStream.h
zuspec_parser-0.0.5.dist-info/LICENSE
zuspec_parser-0.0.5.dist-info/WHEEL
zuspec_parser-0.0.5.dist-info/RECORD
zuspec_parser-0.0.5.dist-info/top_level.txt
zuspec_parser-0.0.5.dist-info/entry_points.txt
zuspec_parser-0.0.5.dist-info/METADATA
