Metadata-Version: 2.1
Name: zuspec-parser
Version: 0.0.5
Summary: Provides a PSS parser and related tools
Author: Matthew Ballance
Author-email: matt.ballance@gmail.com
License-File: LICENSE
Requires-Dist: debug-mgr
Requires-Dist: ciostream
